immanuel/__init__.py
immanuel/charts.py
immanuel/setup.py
immanuel/classes/cache.py
immanuel/classes/localize.py
immanuel/classes/serialize.py
immanuel/classes/wrap.py
immanuel/const/calc.py
immanuel/const/chart.py
immanuel/const/data.py
immanuel/const/dignities.py
immanuel/const/genders.py
immanuel/const/names.py
immanuel/locales/de_DE/mappings.py
immanuel/locales/de_DE/LC_MESSAGES/immanuel.mo
immanuel/locales/es_ES/mappings.py
immanuel/locales/es_ES/LC_MESSAGES/immanuel.mo
immanuel/locales/pt_BR/mappings.py
immanuel/locales/pt_BR/LC_MESSAGES/immanuel.mo
immanuel/reports/aspect.py
immanuel/reports/dignity.py
immanuel/reports/pattern.py
immanuel/reports/weighting.py
immanuel/resources/ephemeris/seas_12.se1
immanuel/resources/ephemeris/seas_18.se1
immanuel/resources/ephemeris/seas_24.se1
immanuel/resources/ephemeris/semo_12.se1
immanuel/resources/ephemeris/semo_18.se1
immanuel/resources/ephemeris/semo_24.se1
immanuel/resources/ephemeris/semo_36.se1
immanuel/resources/ephemeris/semo_42.se1
immanuel/resources/ephemeris/sepl_12.se1
immanuel/resources/ephemeris/sepl_18.se1
immanuel/resources/ephemeris/sepl_24.se1
immanuel/resources/ephemeris/sepl_36.se1
immanuel/resources/ephemeris/sepl_42.se1
immanuel/tools/convert.py
immanuel/tools/date.py
immanuel/tools/ephemeris.py
immanuel/tools/forecast.py
immanuel/tools/midpoint.py
immanuel/tools/position.py
immanuel-1.5.3.dist-info/licenses/LICENSE.md
immanuel-1.5.3.dist-info/METADATA
immanuel-1.5.3.dist-info/WHEEL
immanuel-1.5.3.dist-info/top_level.txt
immanuel-1.5.3.dist-info/RECORD
