Metadata-Version: 2.4
Name: immanuel
Version: 1.5.3
Summary: Quickly produce both human-readable and JSON-formatted astrology chart data based on the Swiss Ephemeris and astro.com.
Author-email: Robert Davies <robert@theriftlab.com>
Project-URL: Homepage, https://github.com/theriftlab/immanuel-python
Project-URL: Documentation, https://github.com/theriftlab/immanuel-python/blob/master/docs/1-overview.md
Project-URL: Bug Tracker, https://github.com/theriftlab/immanuel-python/issues
Keywords: astrology,api,pyswisseph,swisseph,swiss ephemeris,astro.com,astro gold
Classifier: Programming Language :: Python :: 3
Classifier: Operating System :: OS Independent
Requires-Python: >=3.10
License-File: LICENSE.md
Requires-Dist: pyswisseph~=2.10
Requires-Dist: python-dateutil
Requires-Dist: timezonefinder~=5.2
Requires-Dist: pytest
Dynamic: license-file
